coda_api/__init__.py
coda_api/hub.py
coda_api-0.3.5.dist-info/LICENSE
coda_api-0.3.5.dist-info/METADATA
coda_api-0.3.5.dist-info/WHEEL
coda_api-0.3.5.dist-info/top_level.txt
coda_api-0.3.5.dist-info/RECORD
